AUTHORS.rst
CHANGES.rst
LICENSE.rst
MANIFEST.in
README.rst
TODO.rst
setup.cfg
setup.py
birdhousebuilder/__init__.py
birdhousebuilder.recipe.tomcat.egg-info/PKG-INFO
birdhousebuilder.recipe.tomcat.egg-info/SOURCES.txt
birdhousebuilder.recipe.tomcat.egg-info/dependency_links.txt
birdhousebuilder.recipe.tomcat.egg-info/entry_points.txt
birdhousebuilder.recipe.tomcat.egg-info/namespace_packages.txt
birdhousebuilder.recipe.tomcat.egg-info/not-zip-safe
birdhousebuilder.recipe.tomcat.egg-info/requires.txt
birdhousebuilder.recipe.tomcat.egg-info/top_level.txt
birdhousebuilder/recipe/__init__.py
birdhousebuilder/recipe/tomcat/README.txt
birdhousebuilder/recipe/tomcat/__init__.py
birdhousebuilder/recipe/tomcat/logging.properties
birdhousebuilder/recipe/tomcat/server.xml
birdhousebuilder/recipe/tomcat/setenv.sh
birdhousebuilder/recipe/tomcat/tomcat-users.xml
birdhousebuilder/recipe/tomcat/tests/__init__.py
birdhousebuilder/recipe/tomcat/tests/test_doctests.py