Metadata-Version: 1.1
Name: birdhousebuilder.recipe.tomcat
Version: 0.3.3
Summary: A Buildout recipe to install and configure tomcat with conda.
Home-page: https://github.com/bird-house/birdhousebuilder.recipe.tomcat
Author: Birdhouse
Author-email: wps-dev@dkrz.de
License: Apache License 2
Keywords: buildout recipe birdhouse tomcat conda anaconda
Platform: UNKNOWN
Classifier: Framework :: Buildout
Classifier: Intended Audience :: Developers
Classifier: Topic :: Software Development :: Build Tools
Classifier: Topic :: Software Development :: Libraries :: Python Modules
Classifier: License :: OSI Approved :: BSD License
